Metadata-Version: 1.1
Name: spectralview
Version: 0.0.1
Summary: Web application for star spectra viewing.
Home-page: https://spectralview.readthedocs.io/
Author: Ondřej Podsztavek
Author-email: ondrej.podsztavek@gmail.com
License: GPLv3
Keywords: star spectra astroinformatics astronomy
Platform: UNKNOWN
Classifier: Development Status :: 2 - Pre-Alpha
Classifier: License :: OSI Approved :: GNU General Public License v3 (GPLv3)
Classifier: Programming Language :: Python :: 3.5
Classifier: Programming Language :: Python :: 3.6
